LGBtrainer.py
LGBtrainer-0.1.dist-info/LICENSE.txt
LGBtrainer-0.1.dist-info/METADATA
LGBtrainer-0.1.dist-info/WHEEL
LGBtrainer-0.1.dist-info/top_level.txt
LGBtrainer-0.1.dist-info/RECORD
