Metadata-Version: 2.1
Name: LGBtrainer
Version: 0.1
Summary: Find LGBM Hyperparams and train the model
Home-page: https://github.com/Rajshinde07/LGBtrainer
Author: Rajwardhan Shinde
Author-email: rajshinde55553@gmail.com
License: UNKNOWN
Platform: UNKNOWN
Classifier: Programming Language :: Python :: 3
Classifier: Programming Language :: Python :: 3.6
Classifier: Programming Language :: Python :: 3.7
Classifier: License :: OSI Approved :: MIT License
Classifier: Operating System :: OS Independent
